{
  "events":[
    {
      "id":5,
      "name":"Event00005",
      "x":11.5,
      "y":8.5,
      "states":[
        {
          "conditions":[
            
          ],
          "height":1,
          "affixDirection":false,
          "trigger":1,
          "animationType":0,
          "runOnceThenIncrementState":false,
          "cmds":[
            {
              "jsonClass":"ShowText",
              "lines":[
                "Está ficando frio."
              ],
              "useCharacterFace":false,
              "characterId":0
            }
          ]
        }
      ],
      "eventClassId":-1,
      "params":[
        
      ]
    },
    {
      "id":10,
      "name":"Event00010",
      "x":16.5,
      "y":7.5,
      "states":[
        {
          "conditions":[
            
          ],
          "height":1,
          "affixDirection":false,
          "trigger":1,
          "animationType":0,
          "runOnceThenIncrementState":false,
          "cmds":[
            {
              "jsonClass":"ShowText",
              "lines":[
                "Essa neblina não me deixa ver nada."
              ],
              "useCharacterFace":true,
              "characterId":0
            }
          ]
        }
      ],
      "eventClassId":-1,
      "params":[
        
      ]
    },
    {
      "id":24,
      "name":"Event00002",
      "x":19.5,
      "y":12.5,
      "states":[
        {
          "conditions":[
            
          ],
          "height":1,
          "affixDirection":false,
          "trigger":1,
          "animationType":0,
          "runOnceThenIncrementState":false,
          "cmds":[
            {
              "jsonClass":"ShowText",
              "lines":[
                "A mamãe não me deixa brincar com meus amigos antes de terminar as aulas de musica."
              ],
              "customFace":{
                "faceset":"sys/mackie/face_m01a_1.png",
                "faceX":1,
                "faceY":0
              },
              "useCharacterFace":true,
              "characterId":0
            }
          ]
        }
      ],
      "eventClassId":-1,
      "params":[
        
      ]
    },
    {
      "id":25,
      "name":"Event00025",
      "x":25.5,
      "y":19.5,
      "states":[
        {
          "conditions":[
            
          ],
          "height":1,
          "affixDirection":false,
          "trigger":1,
          "animationType":0,
          "runOnceThenIncrementState":false,
          "cmds":[
            {
              "jsonClass":"ShowText",
              "lines":[
                "Preciso guardar estes cobertores..."
              ],
              "useCharacterFace":true,
              "characterId":0
            }
          ]
        }
      ],
      "eventClassId":-1,
      "params":[
        
      ]
    },
    {
      "id":14,
      "name":"Event00014",
      "x":22.5,
      "y":13.5,
      "states":[
        {
          "conditions":[
            
          ],
          "height":1,
          "affixDirection":false,
          "trigger":1,
          "animationType":0,
          "runOnceThenIncrementState":false,
          "cmds":[
            {
              "jsonClass":"ShowText",
              "lines":[
                "Odeio esse sofá sujo e velho."
              ],
              "useCharacterFace":true,
              "characterId":0
            }
          ]
        }
      ],
      "eventClassId":-1,
      "params":[
        
      ]
    },
    {
      "id":20,
      "name":"Event00020",
      "x":25.5,
      "y":11.5,
      "states":[
        {
          "conditions":[
            
          ],
          "height":1,
          "affixDirection":false,
          "trigger":1,
          "animationType":0,
          "runOnceThenIncrementState":false,
          "cmds":[
            {
              "jsonClass":"ShowText",
              "lines":[
                "Gosto desse cobertor."
              ],
              "useCharacterFace":true,
              "characterId":0
            }
          ]
        }
      ],
      "eventClassId":-1,
      "params":[
        
      ]
    },
    {
      "id":6,
      "name":"Event00006",
      "x":20.5,
      "y":11.5,
      "states":[
        {
          "conditions":[
            
          ],
          "height":1,
          "affixDirection":false,
          "trigger":1,
          "animationType":0,
          "runOnceThenIncrementState":false,
          "cmds":[
            {
              "jsonClass":"ShowText",
              "lines":[
                "Sempre me esqueço de molhar as plantas."
              ],
              "useCharacterFace":true,
              "characterId":0
            }
          ]
        }
      ],
      "eventClassId":-1,
      "params":[
        
      ]
    },
    {
      "id":21,
      "name":"Event00020",
      "x":25.5,
      "y":12.5,
      "states":[
        {
          "conditions":[
            
          ],
          "height":1,
          "affixDirection":false,
          "trigger":1,
          "animationType":0,
          "runOnceThenIncrementState":false,
          "cmds":[
            {
              "jsonClass":"ShowText",
              "lines":[
                "Gosto desse cobertor."
              ],
              "useCharacterFace":true,
              "characterId":0
            }
          ]
        }
      ],
      "eventClassId":-1,
      "params":[
        
      ]
    },
    {
      "id":9,
      "name":"Event00009",
      "x":18.5,
      "y":7.5,
      "states":[
        {
          "conditions":[
            
          ],
          "height":1,
          "affixDirection":false,
          "trigger":1,
          "animationType":0,
          "runOnceThenIncrementState":false,
          "cmds":[
            {
              "jsonClass":"ShowText",
              "lines":[
                "Essa neblina não me deixa ver nada."
              ],
              "useCharacterFace":true,
              "characterId":0
            }
          ]
        }
      ],
      "eventClassId":-1,
      "params":[
        
      ]
    },
    {
      "id":13,
      "name":"Event00013",
      "x":22.5,
      "y":15.5,
      "states":[
        {
          "conditions":[
            
          ],
          "height":1,
          "affixDirection":false,
          "trigger":1,
          "animationType":0,
          "runOnceThenIncrementState":false,
          "cmds":[
            {
              "jsonClass":"ShowText",
              "lines":[
                "Odeio esse sofá sujo e velho."
              ],
              "useCharacterFace":true,
              "characterId":0
            }
          ]
        }
      ],
      "eventClassId":-1,
      "params":[
        
      ]
    },
    {
      "id":2,
      "name":"Event00002",
      "x":18.5,
      "y":13.5,
      "states":[
        {
          "conditions":[
            
          ],
          "height":1,
          "affixDirection":false,
          "trigger":1,
          "animationType":0,
          "runOnceThenIncrementState":false,
          "cmds":[
            {
              "jsonClass":"ShowText",
              "lines":[
                "A mamãe não me deixa brincar com meus amigos antes de terminar as aulas de musica."
              ],
              "customFace":{
                "faceset":"sys/mackie/face_m01a_1.png",
                "faceX":1,
                "faceY":0
              },
              "useCharacterFace":true,
              "characterId":0
            }
          ]
        }
      ],
      "eventClassId":-1,
      "params":[
        
      ]
    },
    {
      "id":17,
      "name":"Event00017",
      "x":14.5,
      "y":15.5,
      "states":[
        {
          "conditions":[
            
          ],
          "height":1,
          "affixDirection":false,
          "trigger":1,
          "animationType":0,
          "runOnceThenIncrementState":false,
          "cmds":[
            {
              "jsonClass":"ShowText",
              "lines":[
                "Odeio esse sofá sujo e velho."
              ],
              "useCharacterFace":true,
              "characterId":0
            }
          ]
        }
      ],
      "eventClassId":-1,
      "params":[
        
      ]
    },
    {
      "id":22,
      "name":"Event00002",
      "x":18.5,
      "y":11.5,
      "states":[
        {
          "conditions":[
            
          ],
          "height":1,
          "affixDirection":false,
          "trigger":1,
          "animationType":0,
          "runOnceThenIncrementState":false,
          "cmds":[
            {
              "jsonClass":"ShowText",
              "lines":[
                "A mamãe não me deixa brincar com meus amigos antes de terminar as aulas de musica."
              ],
              "customFace":{
                "faceset":"sys/mackie/face_m01a_1.png",
                "faceX":1,
                "faceY":0
              },
              "useCharacterFace":true,
              "characterId":0
            }
          ]
        }
      ],
      "eventClassId":-1,
      "params":[
        
      ]
    },
    {
      "id":12,
      "name":"Event00012",
      "x":22.5,
      "y":14.5,
      "states":[
        {
          "conditions":[
            
          ],
          "height":1,
          "affixDirection":false,
          "trigger":1,
          "animationType":0,
          "runOnceThenIncrementState":false,
          "cmds":[
            {
              "jsonClass":"ShowText",
              "lines":[
                "Odeio esse sofá sujo e velho."
              ],
              "useCharacterFace":true,
              "characterId":0
            }
          ]
        }
      ],
      "eventClassId":-1,
      "params":[
        
      ]
    },
    {
      "id":7,
      "name":"Event00007",
      "x":24.5,
      "y":8.5,
      "states":[
        {
          "conditions":[
            
          ],
          "height":1,
          "affixDirection":false,
          "trigger":1,
          "animationType":0,
          "runOnceThenIncrementState":false,
          "cmds":[
            {
              "jsonClass":"ShowText",
              "lines":[
                "Sempre me esqueço de molhar as plantas."
              ],
              "useCharacterFace":false,
              "characterId":0
            }
          ]
        }
      ],
      "eventClassId":-1,
      "params":[
        
      ]
    },
    {
      "id":3,
      "name":"Event00003",
      "x":14.5,
      "y":8.5,
      "states":[
        {
          "conditions":[
            
          ],
          "height":1,
          "affixDirection":false,
          "trigger":1,
          "animationType":0,
          "runOnceThenIncrementState":false,
          "cmds":[
            {
              "jsonClass":"ShowText",
              "lines":[
                "Nunca vou ler todos..."
              ],
              "useCharacterFace":true,
              "characterId":0
            }
          ]
        }
      ],
      "eventClassId":-1,
      "params":[
        
      ]
    },
    {
      "id":18,
      "name":"Event00018",
      "x":21.5,
      "y":7.5,
      "states":[
        {
          "conditions":[
            
          ],
          "height":1,
          "affixDirection":false,
          "trigger":1,
          "animationType":0,
          "runOnceThenIncrementState":false,
          "cmds":[
            {
              "jsonClass":"ShowText",
              "lines":[
                "O relógio parou."
              ],
              "useCharacterFace":true,
              "characterId":0
            }
          ]
        }
      ],
      "eventClassId":-1,
      "params":[
        
      ]
    },
    {
      "id":16,
      "name":"Event00016",
      "x":14.5,
      "y":14.5,
      "states":[
        {
          "conditions":[
            
          ],
          "height":1,
          "affixDirection":false,
          "trigger":1,
          "animationType":0,
          "runOnceThenIncrementState":false,
          "cmds":[
            {
              "jsonClass":"ShowText",
              "lines":[
                "Odeio esse sofá sujo e velho."
              ],
              "useCharacterFace":false,
              "characterId":0
            }
          ]
        }
      ],
      "eventClassId":-1,
      "params":[
        
      ]
    },
    {
      "id":11,
      "name":"Event00011",
      "x":20.5,
      "y":7.5,
      "states":[
        {
          "conditions":[
            
          ],
          "height":1,
          "affixDirection":false,
          "trigger":1,
          "animationType":0,
          "runOnceThenIncrementState":false,
          "cmds":[
            {
              "jsonClass":"ShowText",
              "lines":[
                "Essa neblina não me deixa ver nada."
              ],
              "useCharacterFace":true,
              "characterId":0
            }
          ]
        }
      ],
      "eventClassId":-1,
      "params":[
        
      ]
    },
    {
      "id":26,
      "name":"Event00026",
      "x":23.5,
      "y":9.5,
      "states":[
        {
          "conditions":[
            
          ],
          "height":1,
          "affixDirection":false,
          "trigger":2,
          "animationType":0,
          "runOnceThenIncrementState":false,
          "cmds":[
            {
              "jsonClass":"GetChoice",
              "question":[
                "Deseja dormir?"
              ],
              "choices":[
                "Sim",
                "Não"
              ],
              "allowCancel":false,
              "innerCmds":[
                [
                  {
                    "jsonClass":"IfCondition",
                    "conditions":[
                      {
                        "conditionTypeId":1,
                        "intValue1":{
                          "jsonClass":"IntParameter",
                          "constant":0,
                          "valueTypeId":2,
                          "localVariable":"",
                          "globalVariable":"lab_concluido"
                        },
                        "intValue2":{
                          "jsonClass":"IntParameter",
                          "constant":1,
                          "valueTypeId":0,
                          "localVariable":"",
                          "globalVariable":""
                        },
                        "operatorId":0,
                        "negate":false
                      },
                      {
                        "conditionTypeId":1,
                        "intValue1":{
                          "jsonClass":"IntParameter",
                          "constant":0,
                          "valueTypeId":2,
                          "localVariable":"",
                          "globalVariable":"parque_concluidp"
                        },
                        "intValue2":{
                          "jsonClass":"IntParameter",
                          "constant":1,
                          "valueTypeId":0,
                          "localVariable":"",
                          "globalVariable":""
                        },
                        "operatorId":0,
                        "negate":false
                      }
                    ],
                    "elseBranch":true,
                    "trueCmds":[
                      
                    ],
                    "elseCmds":[
                      {
                        "jsonClass":"IfCondition",
                        "conditions":[
                          {
                            "conditionTypeId":1,
                            "intValue1":{
                              "jsonClass":"IntParameter",
                              "constant":0,
                              "valueTypeId":2,
                              "localVariable":"",
                              "globalVariable":"lab_concluido"
                            },
                            "intValue2":{
                              "jsonClass":"IntParameter",
                              "constant":1,
                              "valueTypeId":0,
                              "localVariable":"",
                              "globalVariable":""
                            },
                            "operatorId":0,
                            "negate":false
                          }
                        ],
                        "elseBranch":true,
                        "trueCmds":[
                          {
                            "jsonClass":"Teleport",
                            "loc":{
                              "map":"Map000005.rpgmap",
                              "x":13.5,
                              "y":9.5
                            },
                            "transitionId":1
                          }
                        ],
                        "elseCmds":[
                          {
                            "jsonClass":"Teleport",
                            "loc":{
                              "map":"Map000003.rpgmap",
                              "x":6.5,
                              "y":25.5
                            },
                            "transitionId":1
                          }
                        ]
                      }
                    ]
                  }
                ],
                [
                  
                ],
                [
                  
                ]
              ],
              "useCharacterFace":false,
              "characterId":0
            }
          ]
        }
      ],
      "eventClassId":-1,
      "params":[
        
      ]
    },
    {
      "id":23,
      "name":"Event00002",
      "x":17.5,
      "y":12.5,
      "states":[
        {
          "conditions":[
            
          ],
          "height":1,
          "affixDirection":false,
          "trigger":1,
          "animationType":0,
          "runOnceThenIncrementState":false,
          "cmds":[
            {
              "jsonClass":"ShowText",
              "lines":[
                "A mamãe não me deixa brincar com meus amigos antes de terminar as aulas de musica."
              ],
              "customFace":{
                "faceset":"sys/mackie/face_m01a_1.png",
                "faceX":1,
                "faceY":0
              },
              "useCharacterFace":true,
              "characterId":0
            }
          ]
        }
      ],
      "eventClassId":-1,
      "params":[
        
      ]
    },
    {
      "id":8,
      "name":"Event00008",
      "x":16.5,
      "y":11.5,
      "states":[
        {
          "conditions":[
            
          ],
          "height":1,
          "affixDirection":false,
          "trigger":1,
          "animationType":0,
          "runOnceThenIncrementState":false,
          "cmds":[
            {
              "jsonClass":"ShowText",
              "lines":[
                "Sempre me esqueço de molhar as plantas."
              ],
              "useCharacterFace":true,
              "characterId":0
            }
          ]
        }
      ],
      "eventClassId":-1,
      "params":[
        
      ]
    },
    {
      "id":19,
      "name":"Event00019",
      "x":15.5,
      "y":8.5,
      "states":[
        {
          "conditions":[
            
          ],
          "height":1,
          "affixDirection":false,
          "trigger":1,
          "animationType":0,
          "runOnceThenIncrementState":false,
          "cmds":[
            {
              "jsonClass":"ShowText",
              "lines":[
                "Não preciso trocar de roupas."
              ],
              "useCharacterFace":true,
              "characterId":0
            }
          ]
        }
      ],
      "eventClassId":-1,
      "params":[
        
      ]
    },
    {
      "id":4,
      "name":"Event00004",
      "x":12.5,
      "y":8.5,
      "states":[
        {
          "conditions":[
            
          ],
          "height":1,
          "affixDirection":false,
          "trigger":1,
          "animationType":0,
          "runOnceThenIncrementState":false,
          "cmds":[
            {
              "jsonClass":"ShowText",
              "lines":[
                "Está ficando frio."
              ],
              "useCharacterFace":true,
              "characterId":0
            }
          ]
        }
      ],
      "eventClassId":-1,
      "params":[
        
      ]
    },
    {
      "id":15,
      "name":"Event00015",
      "x":14.5,
      "y":13.5,
      "states":[
        {
          "conditions":[
            
          ],
          "height":1,
          "affixDirection":false,
          "trigger":1,
          "animationType":0,
          "runOnceThenIncrementState":false,
          "cmds":[
            {
              "jsonClass":"ShowText",
              "lines":[
                "Odeio esse sofá sujo e velho."
              ],
              "useCharacterFace":true,
              "characterId":0
            }
          ]
        }
      ],
      "eventClassId":-1,
      "params":[
        
      ]
    }
  ]
}